{
  "subgroup_code": "M38-A",
  "subgroup_label": "Eschatological salvation received by faith",
  "verse_count": 121,
  "vcgs": [
    {
      "provisional_code": "M38-A-VCG-01",
      "context_description": "Christ as Savior: his identity, mission, and office as the singular source of eschatological rescue. These verses name or confess Jesus as Savior (sōtēr), announce his saving mission, or define him by what he came to do — seek the lost, save sinners, save the world. The inner-being state is one of faith, hope, and assurance grounded in who Christ is rather than in any mechanism of reception.",
      "verses": [
        8953,
        8955,
        8956,
        8983,
        9003,
        9043,
        9044,
        9049,
        9053,
        9054,
        9055,
        9056,
        9057,
        9065,
        9066,
        9068
      ],
      "anchor_vc_id": 9043
    },
    {
      "provisional_code": "M38-A-VCG-02",
      "context_description": "Salvation received through faith, confession, calling, and hearing: the inner-being mechanisms by which grace is appropriated. These verses specify heart-belief, mouth-confession, calling on the name, or hearing-and-receiving as the decisive acts through which eschatological rescue is obtained. The self contributes nothing originating from itself; faith is purely receptive.",
      "verses": [
        8952,
        8954,
        8957,
        8961,
        8962,
        8963,
        8964,
        8965,
        8970,
        8971,
        8974,
        8980,
        8987,
        8995,
        8996,
        9009,
        9038,
        51536,
        51538,
        51541,
        51543,
        51549
      ],
      "anchor_vc_id": 8952
    },
    {
      "provisional_code": "M38-A-VCG-03",
      "context_description": "Grace and the free gift as the ground of salvation — dōrea, dōrēma, and gift-language verses. These verses name salvation's ground in the unearned, unmerited divine gift: the Spirit given, righteousness bestowed, grace abounding over sin and death. The inner-being moves from death/guilt/condemnation to life/justification/righteousness entirely through received gift, with no self-originating contribution.",
      "verses": [
        8967,
        8989,
        9073,
        46327,
        46328,
        46329,
        46330,
        46331,
        46334,
        46335,
        46336,
        46341,
        51547,
        51554
      ],
      "anchor_vc_id": 8967
    },
    {
      "provisional_code": "M38-A-VCG-04",
      "context_description": "Salvation as present and ongoing reality in the believer: being-saved now, the community of the saved, and the soul's present rescue. These verses emphasize salvation as a present-tense or progressive state — believers are being saved, the Lord adds the saved daily, the soul is rescued now, the word implanted is saving presently. The inner-being is characterized by ongoing transformation, communal incorporation, and present experience of rescue.",
      "verses": [
        8959,
        8973,
        8978,
        8979,
        8985,
        8991,
        9039,
        9040,
        9070,
        51530,
        51534,
        51535,
        51551,
        51567
      ],
      "anchor_vc_id": 8973
    },
    {
      "provisional_code": "M38-A-VCG-05",
      "context_description": "Salvation through endurance, perseverance, and sustained will under trial. These verses present eschatological salvation as the telos reached by the one who holds fast, endures hatred and persecution to the end, or works out salvation with reverent seriousness. The decisive inner faculty is the persevering will that does not defect under pressure, with salvation as the future state secured by sustained faith.",
      "verses": [
        8975,
        8977,
        8986,
        8988,
        8993,
        8997,
        8999,
        9000,
        9001,
        9008,
        51529,
        51545,
        51555,
        51558,
        51560,
        66065
      ],
      "anchor_vc_id": 8999
    },
    {
      "provisional_code": "M38-A-VCG-06",
      "context_description": "Self-renunciation and surrender as the paradoxical path to eschatological life. These verses share the Synoptic and Johannine inversion: clinging to life for oneself leads to loss, while surrendering life for Christ and the gospel saves it. The inner faculty engaged is the will's willingness to release self-protective interests, and the rescue is the realization of the true eschatological self through that surrender.",
      "verses": [
        9034,
        9035,
        9036,
        9037
      ],
      "anchor_vc_id": 9034
    },
    {
      "provisional_code": "M38-A-VCG-07",
      "context_description": "Human impossibility, divine sufficiency, and the awakened conscience seeking rescue. These verses surface the inner experience of eschatological salvation as humanly unattainable — the astonished question 'who then can be saved?' drives the soul entirely onto God's power. The awakened conscience (the jailer, the disciples, the sinful) is left with nothing but appeal to divine initiative.",
      "verses": [
        8960,
        8998,
        9004,
        9072,
        51528,
        51537,
        51540,
        66064
      ],
      "anchor_vc_id": 9004
    },
    {
      "provisional_code": "M38-A-VCG-08",
      "context_description": "Salvation's scope: universal availability, remnant-election, Israel's rescue, and the expansion to Gentiles. These verses address who is saved and how far salvation reaches — all who call, the elect remnant, all Israel eschatologically, Gentiles receiving what Israel stumbled over, salvation sent to the ends of the earth. The inner-being implication is the removal of ethnic or meritocratic restriction and the grounding of hope in sovereign divine purpose.",
      "verses": [
        8969,
        8972,
        8981,
        8982,
        8984,
        9006,
        51539,
        51542,
        51544,
        51553,
        66066
      ],
      "anchor_vc_id": 8972
    },
    {
      "provisional_code": "M38-A-VCG-09",
      "context_description": "Repentance, godly sorrow, and the inner turning that leads to salvation. These verses identify the will's turning away from sin — through repentance, godly grief, or moral separation from a corrupt generation — as the inner-being movement through which eschatological rescue is entered or maintained. Salvation is the outcome of genuine inner conversion, not merely cognitive assent.",
      "verses": [
        8958,
        9045,
        46326,
        51548
      ],
      "anchor_vc_id": 51548
    },
    {
      "provisional_code": "M38-A-VCG-10",
      "context_description": "Doxological and eschatological completion: salvation declared, praised, and fully possessed. These verses place the inner-being at the consummation point — salvation ascribed to God and the Lamb in heaven, the helmet of salvation worn in battle, Simeon's fulfilled hope, salvation as the soul's final telos received and celebrated. The characteristic inner state is joyful assurance, praise, and rest in completed divine rescue.",
      "verses": [
        8966,
        8976,
        8994,
        9007,
        9041,
        9042,
        9069,
        51531,
        51556,
        51559,
        51568,
        51569
      ],
      "anchor_vc_id": 51531
    }
  ],
  "dual_memberships": [],
  "_repair_meta": {
    "original_parsed_vcgs": 10,
    "missing_resolved": 4,
    "duplicates_resolved": 11,
    "final_distinct": 121
  }
}